pyverless/__init__.py
pyverless/api_gateway_handler/__init__.py
pyverless/api_gateway_handler/api_gateway_handler.py
pyverless/api_gateway_handler/api_gateway_handler_standalone.py
pyverless/auth.py
pyverless/config/__init__.py
pyverless/config/base_settings.py
pyverless/crypto.py
pyverless/decorators.py
pyverless/events_handler/__init__.py
pyverless/events_handler/events_handler.py
pyverless/exceptions.py
pyverless/handlers.py
pyverless/models.py
pyverless/serialization/__init__.py
pyverless/serialization/input_serializer.py
pyverless/serializers.py
pyverless/utils/__init__.py
pyverless/utils/logging.py
pyverless-0.0.57.dist-info/METADATA
pyverless-0.0.57.dist-info/WHEEL
pyverless-0.0.57.dist-info/RECORD
