Metadata-Version: 2.1
Name: pyverless
Version: 0.0.57
Summary: A mini-framework providing tools to help you make complex APIs with serverless
Home-page: https://github.com/QuantumBA/pyverless
License: BSD
Keywords: serverless,api,development
Author: foqum
Author-email: info@foqum.io
Requires-Python: >=3.8,<4.0
Classifier: Development Status :: 4 - Beta
Classifier: Intended Audience :: Developers
Classifier: License :: OSI Approved :: BSD License
Classifier: License :: Other/Proprietary License
Classifier: Programming Language :: Python :: 3
Classifier: Programming Language :: Python :: 3.8
Classifier: Programming Language :: Python :: 3.9
Classifier: Programming Language :: Python :: 3.10
Classifier: Programming Language :: Python :: 3.11
Classifier: Programming Language :: Python :: 3 :: Only
Classifier: Topic :: Software Development :: Build Tools
Requires-Dist: PyJWT (>2.0.0)
Requires-Dist: PyYAML (>=5.1)
Requires-Dist: aws-lambda-powertools (==1.25.7)
Requires-Dist: python-json-logger (>=2.0.7)
Requires-Dist: sentry-sdk (>=0.5.1)
Project-URL: Repository, https://github.com/QuantumBA/pyverless
